Sylphiette/Acessos.py
Sylphiette/Gemini.py
Sylphiette/Terminal.py
Sylphiette/Voices.py
Sylphiette/Vtuber.py
Sylphiette/__init__.py
Sylphiette/base.py
Sylphiette/sylphBot.py
sylphietteia-0.1.1.dist-info/licenses/LICENSE
sylphietteia-0.1.1.dist-info/METADATA
sylphietteia-0.1.1.dist-info/WHEEL
sylphietteia-0.1.1.dist-info/top_level.txt
sylphietteia-0.1.1.dist-info/RECORD
