Metadata-Version: 2.4
Name: SylphietteIA
Version: 0.1.1
Summary: Assistente IA estilo Sylphiette com fala, VTube Studio e Gemini.
Home-page: https://github.com/seuusuario/SylphietteIA
Author: __token__
Author-email: seu@email.com
Classifier: Programming Language :: Python :: 3
Classifier: Operating System :: OS Independent
Requires-Python: >=3.7
License-File: LICENSE
Requires-Dist: pyttsx3
Requires-Dist: google-generativeai
Requires-Dist: websockets
Requires-Dist: PyQt5
Requires-Dist: python-osc
Dynamic: author
Dynamic: author-email
Dynamic: classifier
Dynamic: description
Dynamic: description-content-type
Dynamic: home-page
Dynamic: license-file
Dynamic: requires-dist
Dynamic: requires-python
Dynamic: summary
